fifo.v
module fifo
	#(
	   parameter	DATA_SIZE 	   = 8,	       // number of bits in a data word
				    ADDR_SPACE_EXP = 4	       // number of address bits (2^4 = 16 addresses)
	)
	(
	   input clk,                              // FPGA clock           
	   input reset,                            // reset button
	   input write_to_fifo,                    // signal start writing to FIFO
	   input read_from_fifo,                   // signal start reading from FIFO
	   input [DATA_SIZE-1:0] write_data_in,    // data word into FIFO
	   output [DATA_SIZE-1:0] read_data_out,   // data word out of FIFO
	   output empty,                           // FIFO is empty (no read)
	   output full	                           // FIFO is full (no write)
);

	// signal declaration
	reg [DATA_SIZE-1:0] memory [2**ADDR_SPACE_EXP-1:0];		// memory array register
	reg [ADDR_SPACE_EXP-1:0] current_write_addr, current_write_addr_buff, next_write_addr;
	reg [ADDR_SPACE_EXP-1:0] current_read_addr, current_read_addr_buff, next_read_addr;
	reg fifo_full, fifo_empty, full_buff, empty_buff;
	wire write_enabled;
	
	// register file (memory) write operation
	always @(posedge clk)
		if(write_enabled)
			memory[current_write_addr] <= write_data_in;
			
	// register file (memory) read operation
	assign read_data_out = memory[current_read_addr];
	
	// only allow write operation when FIFO is NOT full
	assign write_enabled = write_to_fifo & ~fifo_full;
	
	// FIFO control logic
	// register logic
	always @(posedge clk or posedge reset)
		if(reset) begin
			current_write_addr 	<= 0;
			current_read_addr 	<= 0;
			fifo_full 			<= 1'b0;
			fifo_empty 			<= 1'b1;       // FIFO is empty after reset
		end
		else begin
			current_write_addr  <= current_write_addr_buff;
			current_read_addr   <= current_read_addr_buff;
			fifo_full  			<= full_buff;
			fifo_empty 			<= empty_buff;
		end

	// next state logic for read and write address pointers
	always @* begin
		// successive pointer values
		next_write_addr = current_write_addr + 1;
		next_read_addr  = current_read_addr + 1;
		
		// default: keep old values
		current_write_addr_buff = current_write_addr;
		current_read_addr_buff  = current_read_addr;
		full_buff  = fifo_full;
		empty_buff = fifo_empty;
		
		// Button press logic
		case({write_to_fifo, read_from_fifo})     // check both buttons
			// 2'b00: neither buttons pressed, do nothing
			
			2'b01:	// read button pressed?
				if(~fifo_empty) begin   // FIFO not empty
					current_read_addr_buff = next_read_addr;
					full_buff = 1'b0;   // after read, FIFO not full anymore
					if(next_read_addr == current_write_addr)
						empty_buff = 1'b1;
				end
			
			2'b10:	// write button pressed?
				if(~fifo_full) begin	// FIFO not full
					current_write_addr_buff = next_write_addr;
					empty_buff = 1'b0;  // after write, FIFO not empty anymore
					if(next_write_addr == current_read_addr)
						full_buff = 1'b1;
				end
				
			2'b11:	begin	// write and read
				current_write_addr_buff = next_write_addr;
				current_read_addr_buff  = next_read_addr;
				end
		endcase			
	end

	// output
	assign full = fifo_full;
	assign empty = fifo_empty;

endmodule

uart_tx.v
module uart_transmitter
    #(
        parameter   DBITS = 8,          // number of data bits
                    SB_TICK = 16        // number of stop bit / oversampling ticks (1 stop bit)
    )
    (
        input clk_50MHz,               
        input reset,                    // reset
        input tx_start,                 // begin data transmission (FIFO NOT empty)
        input sample_tick,              // from baud rate generator
        input [DBITS-1:0] data_in,      // data word from FIFO
        output reg tx_done,             // end of transmission
        output tx                       // transmitter data line
    );
    
    // State Machine States
    localparam [1:0]    idle  = 2'b00,
                        start = 2'b01,
                        data  = 2'b10,
                        stop  = 2'b11;
    
    // Registers                    
    reg [1:0] state, next_state;            // state registers
    reg [3:0] tick_reg, tick_next;          // number of ticks received from baud rate generator
    reg [2:0] nbits_reg, nbits_next;        // number of bits transmitted in data state
    reg [DBITS-1:0] data_reg, data_next;    // assembled data word to transmit serially
    reg tx_reg, tx_next;                    // data filter for potential glitches
    
    // Register Logic
    always @(posedge clk_100MHz, posedge reset)
        if(reset) begin
            state <= idle;
            tick_reg <= 0;
            nbits_reg <= 0;
            data_reg <= 0;
            tx_reg <= 1'b1;
        end
        else begin
            state <= next_state;
            tick_reg <= tick_next;
            nbits_reg <= nbits_next;
            data_reg <= data_next;
            tx_reg <= tx_next;
        end
    
    // State Machine Logic
    always @* begin
        next_state = state;
        tx_done = 1'b0;
        tick_next = tick_reg;
        nbits_next = nbits_reg;
        data_next = data_reg;
        tx_next = tx_reg;
        
        case(state)
            idle: begin                     // no data in FIFO
                tx_next = 1'b1;             // transmit idle
                if(tx_start) begin          // when FIFO is NOT empty
                    next_state = start;
                    tick_next = 0;
                    data_next = data_in;
                end
            end
            
            start: begin
                tx_next = 1'b0;             // start bit
                if(sample_tick)
                    if(tick_reg == 15) begin
                        next_state = data;
                        tick_next = 0;
                        nbits_next = 0;
                    end
                    else
                        tick_next = tick_reg + 1;
            end
            
            data: begin
                tx_next = data_reg[0];
                if(sample_tick)
                    if(tick_reg == 15) begin
                        tick_next = 0;
                        data_next = data_reg >> 1;
                        if(nbits_reg == (DBITS-1))
                            next_state = stop;
                        else
                            nbits_next = nbits_reg + 1;
                    end
                    else
                        tick_next = tick_reg + 1;
            end
            
            stop: begin
                tx_next = 1'b1;         // back to idle
                if(sample_tick)
                    if(tick_reg == (SB_TICK-1)) begin
                        next_state = idle;
                        tx_done = 1'b1;
                    end
                    else
                        tick_next = tick_reg + 1;
            end
        endcase    
    end
    
    // Output Logic
    assign tx = tx_reg;
 
endmodule

landmark_storage.v
// Stores incoming landmark coordinates into register arrays indexed by landmark_id and asserts frame_ready when the last landmark of the frame is received.

module landmark_storage (
    input clk,
    input rst,

    input valid_in,              // new landmark available
    input [4:0] landmark_id,     // 0–20
    input [15:0] x_in,
    input [15:0] y_in,

    output reg frame_ready,      // high when all landmarks for a frame received

    output reg [335:0] x_out,
    output reg [335:0] y_out
);
    reg [4:0] count;
    
    always @(posedge clk) begin
        if (rst) begin
            frame_ready <= 0;
            x_out <= 0;
            y_out <= 0;
            count <= 0;
        end
        else begin
            frame_ready <= 0;
            if (valid_in && count < 21) begin
                x_out[landmark_id * 16 +: 16] <= x_in;
                y_out[landmark_id * 16 +: 16] <= y_in;
                if (count == 20) begin
                    frame_ready <= 1;
                    count <= 0;
                end
                else begin
                    count <= count + 1;
                end
            end
        end
    end

endmodule

fifo_landmark.v
module coord_assembler (
    input  clk,
    input  rst,
    
    // Interface to FIFO
    input  [7:0] fifo_data,
    input  fifo_empty,
    output reg fifo_rd_en,
    
    // Interface to Landmark Storage
    output reg [15:0] x_out,
    output reg [15:0] y_out,
    output reg [4:0]  landmark_id,
    output reg        valid_out
);

    reg [2:0] state, next_state;
    reg [4:0] id_count;
    reg [15:0] x_next, y_next;

    // State definitions
    localparam IDLE   = 3'd0,
               GET_XH = 3'd1,
               GET_XL = 3'd2,
               GET_YH = 3'd3,
               GET_YL = 3'd4;

    always @(posedge clk or posedge rst) begin
        if (rst) begin
            state <= IDLE;
            fifo_rd_en <= 0;
            valid_out <= 0;
            id_count <= 0;
            landmark_id <= 0;
            x_out <= 0;
            y_out <= 0;
        end else begin
            valid_out <= 0; // Default pulse low
            fifo_rd_en <= 0;
            state <= next_state;
            x_out <= x_next;
            y_out <= y_next;
        end
    end
    always @ (*) begin
        x_next = x_out;
        y_next = y_out;
        next_state = state;
        case (state)
                IDLE: begin
                    if (!fifo_empty) begin
                        fifo_rd_en = 1;
                        next_state = GET_XH;
                    end
                end

                GET_XH: begin
                    x_next[15:8] = fifo_data;
                    if (!fifo_empty) begin
                        fifo_rd_en = 1;
                        next_state = GET_XL;
                    end
                end

                GET_XL: begin
                    x_next[7:0] = fifo_data;
                    if (!fifo_empty) begin
                        fifo_rd_en = 1;
                        next_state = GET_YH;
                    end
                end

                GET_YH: begin
                    y_next[15:8] = fifo_data;
                    if (!fifo_empty) begin
                        fifo_rd_en = 1;
                        next_state = GET_YL;
                    end
                end

                GET_YL: begin
                    y_next[7:0] = fifo_data;
                    next_state = IDLE;
                end
            endcase
    end
    always @ (posedge clk) begin
        // Increment ID for next landmark
        if (state == GET_YH) begin
                if (id_count == 20)
                    id_count <= 0;
                else
                    id_count <= id_count + 1;
                landmark_id <= id_count;
                valid_out <= 1; // Coordinate complete!
        end
    end


endmodule

uart_rx.v
module uart_rx 
#( parameter DBITS = 8,
             SB_TICK= 16 //stop bit
)
(input clk_50MHz,
 input reset,
 input rx,
 input sample_tick,
 output reg data_ready,
 output [DBITS-1:0] data_out
) ;

localparam [1:0] idle = 2'b00,
                 start= 2'b01,
                 data = 2'b10,
                 stop = 2'b11;
reg [1:0] state, next_state;
reg [3:0] tick_reg, tick_next;
reg [2:0] nbits_reg, nbits_next;
reg [7:0] data_reg ,data_next;
reg rx_sync_1, rx_sync_2;
always @(posedge clk_50MHz) begin
    rx_sync_1 <= rx;
    rx_sync_2 <= rx_sync_1; // Use rx_sync_2 in your FSM instead of rx
end
//Register Logic
always @(posedge clk_50MHz, posedge reset) begin
    if (reset) begin
        state <=idle;
        tick_reg<=0;
        nbits_reg<=0;
        data_reg<=0;
    end
    else begin
        state<=next_state;
        tick_reg<=tick_next;
        nbits_reg<=nbits_next;
        data_reg<=data_next;
    end
end
//State Machine logic
always@(*) begin
    next_state=state;
    data_ready=1'b0;
    tick_next= tick_reg;
    nbits_next= nbits_reg;
    data_next= data_reg;

    case(state)
        idle:begin
            if(~rx_sync_2) begin
                next_state= start;
                tick_next= 0;
            end
        end
        start: begin 
            if(sample_tick)begin
                if(tick_reg==7) begin
                    next_state=data;
                    tick_next=0;
                    nbits_next=0;
                end
                else begin
                    tick_next=tick_reg + 1;
                end
            end
        end

        data: begin
            if(sample_tick) begin
                if(tick_reg==15) begin
                    tick_next=0;
                    data_next={rx_sync_2,data_reg[7:1]};
                    if(nbits_reg== (DBITS-1))
                        next_state=stop;
                    else 
                        nbits_next=nbits_reg+1;
                end
                else    tick_next=tick_reg+1;
            end
        end
        stop:begin
            if(sample_tick) begin
                if(tick_reg==(SB_TICK-1)) begin
                    next_state=idle;
                    data_ready=1'b1;
                end
                else 
                    tick_next=tick_reg+1;
            end
        end
    endcase
end

assign data_out=data_reg;
endmodule

baud_generator.v
module baud_rate_generator
    #(              // 115200 baud
        parameter   N = 5,     // number of counter bits
                    M = 27     // counter limit value
    )
    (
        input clk_50MHz,       // DE-10 clock
        input reset,            // reset
        output tick             // sample tick
    );
    
    // Counter Register
    reg [N-1:0] counter;        // counter value
    wire [N-1:0] next;          // next counter value
    
    // Register Logic
    always @(posedge clk_50MHz, posedge reset)
        if(reset)
            counter <= 0;
        else
            counter <= next;
            
    // Next Counter Value Logic
    assign next = (counter == (M-1)) ? 0 : counter + 1;
    
    // Output Logic
    assign tick = (counter == (M-1)) ? 1'b1 : 1'b0;
       
endmodule

uart_top.v
module uart_top
    #(
        parameter   DBITS = 8,          
                    SB_TICK = 16,       
                    BR_LIMIT = 27,     
                    BR_BITS = 5,       
                    FIFO_EXP = 7        
    )
    (
        input clk_50MHz,               
        input reset,                    
        input write_uart,               // Remains for TX (sending data back)
        input rx,                       
        input [DBITS-1:0] write_data,   
        output tx,                      
        
        // Landmark Outputs
        output frame_ready,             // High when all 21 points are stored
        output [335:0] landmarks_x,     // Full X vector for the recognizer
        output [335:0] landmarks_y      // Full Y vector for the recognizer
    );
    
    // Internal Connection Signals
    wire tick;                          
    wire rx_done_tick;                  
    wire tx_done_tick;                  
    wire tx_empty;                      
    wire tx_fifo_not_empty;             
    wire [DBITS-1:0] tx_fifo_out;       
    wire [DBITS-1:0] rx_data_out;       
    wire [DBITS-1:0] fifo_rx_data;      // Data leaving FIFO
    wire rx_empty;                      // FIFO status
    
    // Assembler to Storage Wires
    wire [15:0] assemble_x, assemble_y;
    wire [4:0]  assemble_id;
    wire        assemble_valid;
    wire        fifo_rd_en;             // Automated read signal from Assembler

    // 1. Baud Rate Generator
    baud_rate_generator #( .M(BR_LIMIT), .N(BR_BITS) ) BAUD_RATE_GEN (
        .clk_50MHz(clk_50MHz), .reset(reset), .tick(tick)
    );
    
    // 2. UART Receiver
    uart_rx #( .DBITS(DBITS), .SB_TICK(SB_TICK) ) UART_RX_UNIT (
        .clk_50MHz(clk_50MHz), .reset(reset), .rx(rx),
        .sample_tick(tick), .data_ready(rx_done_tick), .data_out(rx_data_out)
    );
    
    // 3. FIFO Receiver Buffer
    fifo #( .DATA_SIZE(DBITS), .ADDR_SPACE_EXP(FIFO_EXP) ) FIFO_RX_UNIT (
        .clk(clk_50MHz), .reset(reset),
        .write_to_fifo(rx_done_tick),   // Written by UART_RX
        .read_from_fifo(fifo_rd_en),    // Read by Assembler
        .write_data_in(rx_data_out),
        .read_data_out(fifo_rx_data),
        .empty(rx_empty),
        .full()                         // Open
    );

    // 4. Coordinate Assembler 
    // Takes 8-bit bytes from FIFO, outputs 16-bit X, Y
    coord_assembler ASSEMBLER_UNIT (
        .clk(clk_50MHz), .rst(reset),
        .fifo_data(fifo_rx_data),
        .fifo_empty(rx_empty),
        .fifo_rd_en(fifo_rd_en),
        .x_out(assemble_x), .y_out(assemble_y),
        .landmark_id(assemble_id),
        .valid_out(assemble_valid)
    );

    // 5. Landmark Storage 
    // Takes 16-bit points, stores them in the 336-bit vector
    landmark_storage STORAGE_UNIT (
        .clk(clk_50MHz), .rst(reset),
        .valid_in(assemble_valid),
        .landmark_id(assemble_id),
        .x_in(assemble_x), .y_in(assemble_y),
        .frame_ready(frame_ready),
        .x_out(landmarks_x),
        .y_out(landmarks_y)
    );
    
    // 6. UART Transmitter (For sending results back to PC)
    uart_transmitter #( .DBITS(DBITS), .SB_TICK(SB_TICK) ) UART_TX_UNIT (
        .clk_50MHz(clk_50MHz), .reset(reset),
        .tx_start(tx_fifo_not_empty), .sample_tick(tick),
        .data_in(tx_fifo_out), .tx_done(tx_done_tick), .tx(tx)
    );
    
    // 7. FIFO Transmitter Buffer
    fifo #( .DATA_SIZE(DBITS), .ADDR_SPACE_EXP(FIFO_EXP) ) FIFO_TX_UNIT (
        .clk(clk_50MHz), .reset(reset),
        .write_to_fifo(write_uart),
        .read_from_fifo(tx_done_tick),
        .write_data_in(write_data),
        .read_data_out(tx_fifo_out),
        .empty(tx_empty),
        .full()                
    );

    assign tx_fifo_not_empty = ~tx_empty;
  
endmodule

uart_tb.v
`timescale 1ns / 1ps

module uart_top_tb();
    reg clk_50MHz, reset, rx, write_uart;
    reg [7:0] write_data;
    
    wire tx, frame_ready;
    wire [335:0] landmarks_x;
    wire [335:0] landmarks_y;

    // 50MHz Clock
    always #10 clk_50MHz = ~clk_50MHz;

    // Instantiate the UPDATED Top Module
    uart_top #(
        .BR_LIMIT(27),     
        .FIFO_EXP(7)       
    ) dut (
        .clk_50MHz(clk_50MHz), 
        .reset(reset), 
        .rx(rx), 
        .write_data(write_data),
        .write_uart(write_uart),
        .tx(tx),
        .frame_ready(frame_ready),
        .landmarks_x(landmarks_x),
        .landmarks_y(landmarks_y)
    );

    initial begin
        $dumpfile("uart_sim.vcd");
        $dumpvars(0, uart_top_tb);
        
        // Initialize
        clk_50MHz = 0; reset = 1; rx = 1; 
        write_uart = 0; write_data = 0;
        
        #100 reset = 0; 
        #200;

        // --- TEST CASE: Send Landmark 0 ---
        // X = 1234, Y = 5678
        send_byte(8'h12); // X High
        send_byte(8'h34); // X Low
        send_byte(8'h56); // Y High
        send_byte(8'h78); // Y Low
        
        // --- TEST CASE: Send Landmark 1 ---
        // X = ABCD, Y = EF01
        send_byte(8'hAB); // X High
        send_byte(8'hCD); // X Low
        send_byte(8'hEF); // Y High
        send_byte(8'h01); // Y Low

        // Wait for the pipeline to process
        #2000;

        // Simulate sending a "Result" back via TX
        write_data = 8'hA5; // Result code
        write_uart = 1;
        #20 write_uart = 0;

        // Wait for the TX wire to finish toggling (approx 10 bits * 8680ns)
        #100000;

        $display("Check GTKWave: landmarks_x[15:0] should be 1234");
        $display("Check GTKWave: landmarks_x[31:16] should be ABCD");
        $finish;
    end

    // Task for 115200 baud bit-banging
    task send_byte(input [7:0] data);
        integer i;
        begin
            rx = 0; // Start
            #(8680);
            for (i=0; i<8; i=i+1) begin
                rx = data[i]; 
                #(8680);
            end
            rx = 1; // Stop
            #(8680);
            #1000; // Small gap between bytes
        end
    endtask

endmodule

uart_sim.vcd
$date
	Fri Mar 27 11:18:21 2026
$end
$version
	Icarus Verilog
$end
$timescale
	1ps
$end
$scope module uart_top_tb $end
$var wire 1 ! tx $end
$var wire 336 " landmarks_y [335:0] $end
$var wire 336 # landmarks_x [335:0] $end
$var wire 1 $ frame_ready $end
$var reg 1 % clk_50MHz $end
$var reg 1 & reset $end
$var reg 1 ' rx $end
$var reg 8 ( write_data [7:0] $end
$var reg 1 ) write_uart $end
$scope module dut $end
$var wire 1 % clk_50MHz $end
$var wire 1 & reset $end
$var wire 1 ' rx $end
$var wire 1 * tx_fifo_not_empty $end
$var wire 8 + write_data [7:0] $end
$var wire 1 ) write_uart $end
$var wire 8 , tx_fifo_out [7:0] $end
$var wire 1 - tx_empty $end
$var wire 1 . tx_done_tick $end
$var wire 1 ! tx $end
$var wire 1 / tick $end
$var wire 1 0 rx_empty $end
$var wire 1 1 rx_done_tick $end
$var wire 8 2 rx_data_out [7:0] $end
$var wire 336 3 landmarks_y [335:0] $end
$var wire 336 4 landmarks_x [335:0] $end
$var wire 1 $ frame_ready $end
$var wire 8 5 fifo_rx_data [7:0] $end
$var wire 1 6 fifo_rd_en $end
$var wire 16 7 assemble_y [15:0] $end
$var wire 16 8 assemble_x [15:0] $end
$var wire 1 9 assemble_valid $end
$var wire 5 : assemble_id [4:0] $end
$var parameter 32 ; BR_BITS $end
$var parameter 32 < BR_LIMIT $end
$var parameter 32 = DBITS $end
$var parameter 32 > FIFO_EXP $end
$var parameter 32 ? SB_TICK $end
$scope module ASSEMBLER_UNIT $end
$var wire 1 % clk $end
$var wire 1 & rst $end
$var wire 1 0 fifo_empty $end
$var wire 8 @ fifo_data [7:0] $end
$var parameter 3 A GET_XH $end
$var parameter 3 B GET_XL $end
$var parameter 3 C GET_YH $end
$var parameter 3 D GET_YL $end
$var parameter 3 E IDLE $end
$var reg 1 6 fifo_rd_en $end
$var reg 5 F id_count [4:0] $end
$var reg 5 G landmark_id [4:0] $end
$var reg 3 H next_state [2:0] $end
$var reg 3 I state [2:0] $end
$var reg 1 9 valid_out $end
$var reg 16 J x_next [15:0] $end
$var reg 16 K x_out [15:0] $end
$var reg 16 L y_next [15:0] $end
$var reg 16 M y_out [15:0] $end
$upscope $end
$scope module BAUD_RATE_GEN $end
$var wire 1 % clk_50MHz $end
$var wire 1 & reset $end
$var wire 1 / tick $end
$var wire 5 N next [4:0] $end
$var parameter 32 O M $end
$var parameter 32 P N $end
$var reg 5 Q counter [4:0] $end
$upscope $end
$scope module FIFO_RX_UNIT $end
$var wire 1 % clk $end
$var wire 1 0 empty $end
$var wire 1 R full $end
$var wire 8 S read_data_out [7:0] $end
$var wire 1 6 read_from_fifo $end
$var wire 1 & reset $end
$var wire 1 T write_enabled $end
$var wire 1 1 write_to_fifo $end
$var wire 8 U write_data_in [7:0] $end
$var parameter 32 V ADDR_SPACE_EXP $end
$var parameter 32 W DATA_SIZE $end
$var reg 7 X current_read_addr [6:0] $end
$var reg 7 Y current_read_addr_buff [6:0] $end
$var reg 7 Z current_write_addr [6:0] $end
$var reg 7 [ current_write_addr_buff [6:0] $end
$var reg 1 \ empty_buff $end
$var reg 1 ] fifo_empty $end
$var reg 1 ^ fifo_full $end
$var reg 1 _ full_buff $end
$var reg 7 ` next_read_addr [6:0] $end
$var reg 7 a next_write_addr [6:0] $end
$upscope $end
$scope module FIFO_TX_UNIT $end
$var wire 1 % clk $end
$var wire 1 b full $end
$var wire 8 c read_data_out [7:0] $end
$var wire 1 & reset $end
$var wire 8 d write_data_in [7:0] $end
$var wire 1 e write_enabled $end
$var wire 1 ) write_to_fifo $end
$var wire 1 . read_from_fifo $end
$var wire 1 - empty $end
$var parameter 32 f ADDR_SPACE_EXP $end
$var parameter 32 g DATA_SIZE $end
$var reg 7 h current_read_addr [6:0] $end
$var reg 7 i current_read_addr_buff [6:0] $end
$var reg 7 j current_write_addr [6:0] $end
$var reg 7 k current_write_addr_buff [6:0] $end
$var reg 1 l empty_buff $end
$var reg 1 - fifo_empty $end
$var reg 1 m fifo_full $end
$var reg 1 n full_buff $end
$var reg 7 o next_read_addr [6:0] $end
$var reg 7 p next_write_addr [6:0] $end
$upscope $end
$scope module STORAGE_UNIT $end
$var wire 1 % clk $end
$var wire 5 q landmark_id [4:0] $end
$var wire 1 & rst $end
$var wire 1 9 valid_in $end
$var wire 16 r x_in [15:0] $end
$var wire 16 s y_in [15:0] $end
$var reg 5 t count [4:0] $end
$var reg 1 $ frame_ready $end
$var reg 336 u x_out [335:0] $end
$var reg 336 v y_out [335:0] $end
$upscope $end
$scope module UART_RX_UNIT $end
$var wire 1 % clk_50MHz $end
$var wire 8 w data_out [7:0] $end
$var wire 1 & reset $end
$var wire 1 ' rx $end
$var wire 1 / sample_tick $end
$var parameter 32 x DBITS $end
$var parameter 32 y SB_TICK $end
$var parameter 2 z data $end
$var parameter 2 { idle $end
$var parameter 2 | start $end
$var parameter 2 } stop $end
$var reg 8 ~ data_next [7:0] $end
$var reg 1 1 data_ready $end
$var reg 8 !" data_reg [7:0] $end
$var reg 3 "" nbits_next [2:0] $end
$var reg 3 #" nbits_reg [2:0] $end
$var reg 2 $" next_state [1:0] $end
$var reg 1 %" rx_sync_1 $end
$var reg 1 &" rx_sync_2 $end
$var reg 2 '" state [1:0] $end
$var reg 4 (" tick_next [3:0] $end
$var reg 4 )" tick_reg [3:0] $end
$upscope $end
$scope module UART_TX_UNIT $end
$var wire 1 % clk_50MHz $end
$var wire 8 *" data_in [7:0] $end
$var wire 1 & reset $end
$var wire 1 / sample_tick $end
$var wire 1 ! tx $end
$var wire 1 * tx_start $end
$var parameter 32 +" DBITS $end
$var parameter 32 ," SB_TICK $end
$var parameter 2 -" data $end
$var parameter 2 ." idle $end
$var parameter 2 /" start $end
$var parameter 2 0" stop $end
$var reg 8 1" data_next [7:0] $end
$var reg 8 2" data_reg [7:0] $end
$var reg 3 3" nbits_next [2:0] $end
$var reg 3 4" nbits_reg [2:0] $end
$var reg 2 5" next_state [1:0] $end
$var reg 2 6" state [1:0] $end
$var reg 4 7" tick_next [3:0] $end
$var reg 4 8" tick_reg [3:0] $end
$var reg 1 . tx_done $end
$var reg 1 9" tx_next $end
$var reg 1 :" tx_reg $end
$upscope $end
$upscope $end
$scope task send_byte $end
$var reg 8 ;" data [7:0] $end
$var integer 32 <" i [31:0] $end
$upscope $end
$upscope $end
$enddefinitions $end
$comment Show the parameter values. $end
$dumpall
b11 0"
b1 /"
b0 ."
b10 -"
b10000 ,"
b1000 +"
b11 }
b1 |
b0 {
b10 z
b10000 y
b1000 x
b1000 g
b111 f
b1000 W
b111 V
b101 P
b11011 O
b0 E
b100 D
b11 C
b10 B
b1 A
b10000 ?
b111 >
b1000 =
b11011 <
b101 ;
$end
#0
$dumpvars
bx <"
bx ;"
1:"
19"
b0 8"
b0 7"
b0 6"
b0 5"
b0 4"
b0 3"
b0 2"
b0 1"
bx *"
b0 )"
b0 ("
b0 '"
x&"
x%"
b0 $"
b0 #"
b0 ""
b0 !"
b0 ~
b0 w
bx v
bx u
bx t
b0 s
b0 r
b0 q
b1 p
b1 o
0n
0m
1l
b0 k
b0 j
b0 i
b0 h
0e
b0 d
bx c
0b
b1 a
b1 `
0_
0^
1]
1\
b0 [
b0 Z
b0 Y
b0 X
b0 U
0T
bx S
0R
b0 Q
b1 N
b0 M
b0 L
b0 K
b0 J
b0 I
b0 H
b0 G
b0 F
bx @
b0 :
09
b0 8
b0 7
06
bx 5
bx 4
bx 3
b0 2
01
10
0/
0.
1-
bx ,
b0 +
0*
0)
b0 (
1'
1&
0%
x$
bx #
bx "
1!
$end
#10000
1%"
b0 t
b0 "
b0 3
b0 v
b0 #
b0 4
b0 u
0$
1%
#20000
0%
#30000
1&"
1%
#40000
0%
#50000
1%
#60000
0%
#70000
1%
#80000
0%
#90000
1%
#100000
0%
0&
#110000
b10 N
b1 Q
1%
#120000
0%
#130000
b11 N
b10 Q
1%
#140000
0%
#150000
b100 N
b11 Q
1%
#160000
0%
#170000
b101 N
b100 Q
1%
#180000
0%
#190000
b110 N
b101 Q
1%
#200000
0%
#210000
b111 N
b110 Q
1%
#220000
0%
#230000
b1000 N
b111 Q
1%
#240000
0%
#250000
b1001 N
b1000 Q
1%
#260000
0%
#270000
b1010 N
b1001 Q
1%
#280000
0%
#290000
b1011 N
b1010 Q
1%
#300000
0%
0'
b10010 ;"
#310000
b1100 N
0%"
b1011 Q
1%
#320000
0%
#330000
b1 $"
b1101 N
0&"
b1100 Q
1%
#340000
0%
#350000
b1110 N
b1101 Q
b1 '"
1%
#360000
0%
#370000
b1111 N
b1110 Q
1%
#380000
0%
#390000
b10000 N
b1111 Q
1%
#400000
0%
#410000
b10001 N
b10000 Q
1%
#420000
0%
#430000
b10010 N
b10001 Q
1%
#440000
0%
#450000
b10011 N
b10010 Q
1%
#460000
0%
#470000
b10100 N
b10011 Q
1%
#480000
0%
#490000
b10101 N
b10100 Q
1%
#500000
0%
#510000
b10110 N
b10101 Q
1%
#520000
0%
#530000
b10111 N
b10110 Q
1%
#540000
0%
#550000
b11000 N
b10111 Q
1%
#560000
0%
#570000
b11001 N
b11000 Q
1%
#580000
0%
#590000
b11010 N
b11001 Q
1%
#600000
0%
#610000
b1 ("
b0 N
1/
b11010 Q
1%
#620000
0%
#630000
b1 N
0/
b1 ("
b0 Q
b1 )"
1%
#640000
0%
#650000
b10 N
b1 Q
1%
#660000
0%
#670000
b11 N
b10 Q
1%
#680000
0%
#690000
b100 N
b11 Q
1%
#700000
0%
#710000
b101 N
b100 Q
1%
#720000
0%
#730000
b110 N
b101 Q
1%
#740000
0%
#750000
b111 N
b110 Q
1%
#760000
0%
#770000
b1000 N
b111 Q
1%
#780000
0%
#790000
b1001 N
b1000 Q
1%
#800000
0%
#810000
b1010 N
b1001 Q
1%
#820000
0%
#830000
b1011 N
b1010 Q
1%
#840000
0%
#850000
b1100 N
b1011 Q
1%
#860000
0%
#870000
b1101 N
b1100 Q
1%
#880000
0%
#890000
b1110 N
b1101 Q
1%
#900000
0%
#910000
b1111 N
b1110 Q
1%
#920000
0%
#930000
b10000 N
b1111 Q
1%
#940000
0%
#950000
b10001 N
b10000 Q
1%
#960000
0%
#970000
b10010 N
b10001 Q
1%
#980000
0%
#990000
b10011 N
b10010 Q
1%
#1000000
0%
#1010000
b10100 N
b10011 Q
1%
#1020000
0%
#1030000
b10101 N
b10100 Q
1%
#1040000
0%
#1050000
b10110 N
b10101 Q
1%
#1060000
0%
#1070000
b10111 N
b10110 Q
1%
#1080000
0%
#1090000
b11000 N
b10111 Q
1%
#1100000
0%
#1110000
b11001 N
b11000 Q
1%
#1120000
0%
#1130000
b11010 N
b11001 Q
1%
#1140000
0%
#1150000
b10 ("
b0 N
1/
b11010 Q
1%
#1160000
0%
#1170000
b1 N
0/
b10 )"
b0 Q
1%
#1180000
0%
#1190000
b10 N
b1 Q
1%
#1200000
0%
#1210000
b11 N
b10 Q
1%
#1220000
0%
#1230000
b100 N
b11 Q
1%
#1240000
0%
#1250000
b101 N
b100 Q
1%
#1260000
0%
#1270000
b110 N
b101 Q
1%
#1280000
0%
#1290000
b111 N
b110 Q
1%
#1300000
0%
#1310000
b1000 N
b111 Q
1%
#1320000
0%
#1330000
b1001 N
b1000 Q
1%
#1340000
0%
#1350000
b1010 N
b1001 Q
1%
#1360000
0%
#1370000
b1011 N
b1010 Q
1%
#1380000
0%
#1390000
b1100 N
b1011 Q
1%
#1400000
0%
#1410000
b1101 N
b1100 Q
1%
#1420000
0%
#1430000
b1110 N
b1101 Q
1%
#1440000
0%
#1450000
b1111 N
b1110 Q
1%
#1460000
0%
#1470000
b10000 N
b1111 Q
1%
#1480000
0%
#1490000
b10001 N
b10000 Q
1%
#1500000
0%
#1510000
b10010 N
b10001 Q
1%
#1520000
0%
#1530000
b10011 N
b10010 Q
1%
#1540000
0%
#1550000
b10100 N
b10011 Q
1%
#1560000
0%
#1570000
b10101 N
b10100 Q
1%
#1580000
0%
#1590000
b10110 N
b10101 Q
1%
#1600000
0%
#1610000
b10111 N
b10110 Q
1%
#1620000
0%
#1630000
b11000 N
b10111 Q
1%
#1640000
0%
#1650000
b11001 N
b11000 Q
1%
#1660000
0%
#1670000
b11010 N
b11001 Q
1%
#1680000
0%
#1690000
b11 ("
b0 N
1/
b11010 Q
1%
#1700000
0%
#1710000
b1 N
0/
b11 ("
b0 Q
b11 )"
1%
#1720000
0%
#1730000
b10 N
b1 Q
1%
#1740000
0%
#1750000
b11 N
b10 Q
1%
#1760000
0%
#1770000
b100 N
b11 Q
1%
#1780000
0%
#1790000
b101 N
b100 Q
1%
#1800000
0%
#1810000
b110 N
b101 Q
1%
#1820000
0%
#1830000
b111 N
b110 Q
1%
#1840000
0%
#1850000
b1000 N
b111 Q
1%
#1860000
0%
#1870000
b1001 N
b1000 Q
1%
#1880000
0%
#1890000
b1010 N
b1001 Q
1%
#1900000
0%
#1910000
b1011 N
b1010 Q
1%
#1920000
0%
#1930000
b1100 N
b1011 Q
1%
#1940000
0%
#1950000
b1101 N
b1100 Q
1%
#1960000
0%
#1970000
b1110 N
b1101 Q
1%
#1980000
0%
#1990000
b1111 N
b1110 Q
1%
#2000000
0%
#2010000
b10000 N
b1111 Q
1%
#2020000
0%
#2030000
b10001 N
b10000 Q
1%
#2040000
0%
#2050000
b10010 N
b10001 Q
1%
#2060000
0%
#2070000
b10011 N
b10010 Q
1%
#2080000
0%
#2090000
b10100 N
b10011 Q
1%
#2100000
0%
#2110000
b10101 N
b10100 Q
1%
#2120000
0%
#2130000
b10110 N
b10101 Q
1%
#2140000
0%
#2150000
b10111 N
b10110 Q
1%
#2160000
0%
#2170000
b11000 N
b10111 Q
1%
#2180000
0%
